tc_analyzer_lib/__init__.py
tc_analyzer_lib/publish_on_success.py
tc_analyzer_lib/tc_analyzer.py
tc_analyzer_lib/DB_operations/__init__.py
tc_analyzer_lib/DB_operations/mongo_neo4j_ops.py
tc_analyzer_lib/DB_operations/mongodb_access.py
tc_analyzer_lib/DB_operations/mongodb_interaction.py
tc_analyzer_lib/DB_operations/network_graph.py
tc_analyzer_lib/algorithms/__init__.py
tc_analyzer_lib/algorithms/analytics_interactions_script.py
tc_analyzer_lib/algorithms/compute_interaction_matrix_discord.py
tc_analyzer_lib/algorithms/compute_member_activity.py
tc_analyzer_lib/algorithms/member_activity_history.py
tc_analyzer_lib/algorithms/assessment/__init__.py
tc_analyzer_lib/algorithms/assessment/assess_active.py
tc_analyzer_lib/algorithms/assessment/assess_connected.py
tc_analyzer_lib/algorithms/assessment/assess_consistent.py
tc_analyzer_lib/algorithms/assessment/assess_dropped.py
tc_analyzer_lib/algorithms/assessment/assess_lurker.py
tc_analyzer_lib/algorithms/assessment/assess_overlap.py
tc_analyzer_lib/algorithms/assessment/assess_remainder.py
tc_analyzer_lib/algorithms/assessment/assess_still_active.py
tc_analyzer_lib/algorithms/assessment/assess_vital.py
tc_analyzer_lib/algorithms/assessment/check_past.py
tc_analyzer_lib/algorithms/assessment/check_prev_period.py
tc_analyzer_lib/algorithms/assessment/engagement.py
tc_analyzer_lib/algorithms/assessment/utils/__init__.py
tc_analyzer_lib/algorithms/assessment/utils/activity.py
tc_analyzer_lib/algorithms/assessment/utils/compute_interaction_per_acc.py
tc_analyzer_lib/algorithms/assessment/utils/generate_graph.py
tc_analyzer_lib/algorithms/neo4j_analysis/__init__.py
tc_analyzer_lib/algorithms/neo4j_analysis/analyzer_node_stats.py
tc_analyzer_lib/algorithms/neo4j_analysis/centrality.py
tc_analyzer_lib/algorithms/neo4j_analysis/closeness_centrality.py
tc_analyzer_lib/algorithms/neo4j_analysis/local_clustering_coefficient.py
tc_analyzer_lib/algorithms/neo4j_analysis/louvain.py
tc_analyzer_lib-1.4.16.dist-info/METADATA
tc_analyzer_lib-1.4.16.dist-info/WHEEL
tc_analyzer_lib-1.4.16.dist-info/top_level.txt
tc_analyzer_lib-1.4.16.dist-info/RECORD
